remote_event_bundle/__init__.py
remote_event_bundle/backend/__init__.py
remote_event_bundle/backend/kafka_backend.py
remote_event_bundle/bundle.py
remote_event_bundle/event.py
remote_event_bundle-2.1.0.dist-info/LICENSE
remote_event_bundle-2.1.0.dist-info/WHEEL
remote_event_bundle-2.1.0.dist-info/METADATA
remote_event_bundle-2.1.0.dist-info/RECORD
