Metadata-Version: 2.1
Name: remote-event-bundle
Version: 2.1.0
Summary: Remote events
License: Apache
Author: Alvaro Garcia
Author-email: maxpowel@gmail.com
Requires-Python: >=3.6,<4.0
Classifier: License :: Other/Proprietary License
Classifier: Programming Language :: Python :: 3
Classifier: Programming Language :: Python :: 3.6
Classifier: Programming Language :: Python :: 3.7
Classifier: Programming Language :: Python :: 3.8
Classifier: Programming Language :: Python :: 3.9
Requires-Dist: applauncher (>=2.0.1,<3.0.0)
